abtk-0.4.0.dist-info/licenses/LICENSE
core/base_cluster_test.py
core/base_test_processor.py
core/data_types.py
core/quantile_test_result.py
core/test_result.py
tests/nonparametric/__init__.py
tests/nonparametric/bootstrap_test.py
tests/nonparametric/clustered_bootstrap_test.py
tests/nonparametric/paired_bootstrap_test.py
tests/nonparametric/post_normed_bootstrap_test.py
tests/parametric/__init__.py
tests/parametric/ancova_test.py
tests/parametric/clustered_ancova_test.py
tests/parametric/clustered_ttest.py
tests/parametric/clustered_ztest.py
tests/parametric/cuped_ttest.py
tests/parametric/paired_ttest.py
tests/parametric/ttest.py
tests/parametric/ztest.py
utils/cluster_utils.py
utils/corrections.py
utils/data_validation.py
utils/dataframe_helpers.py
utils/effect_simulator.py
utils/effect_size.py
utils/power_analysis.py
utils/quantile_analysis.py
utils/sample_size_calculator.py
utils/simulation.py
utils/visualization.py
utils/bootstrap/__init__.py
utils/bootstrap/generator.py
utils/bootstrap/statistics.py
utils/tests/test_corrections.py
visualization/plotting.py
abtk-0.4.0.dist-info/METADATA
abtk-0.4.0.dist-info/WHEEL
abtk-0.4.0.dist-info/top_level.txt
abtk-0.4.0.dist-info/RECORD
