Metadata-Version: 2.4
Name: abtk
Version: 0.4.0
Summary: A/B Testing Toolkit - Statistical analysis library for A/B tests
Home-page: https://github.com/alexeiveselov92/abtk
Author: Alexei Veselov
Author-email: Alexei Veselov <alexeiveselov92@gmail.com>
License: MIT
Project-URL: Homepage, https://github.com/alexeiveselov92/abtk
Project-URL: Documentation, https://github.com/alexeiveselov92/abtk/blob/main/docs/README.md
Project-URL: Repository, https://github.com/alexeiveselov92/abtk
Project-URL: Bug Reports, https://github.com/alexeiveselov92/abtk/issues
Keywords: ab-testing,statistics,hypothesis-testing,experimentation,analytics
Classifier: Development Status :: 3 - Alpha
Classifier: Intended Audience :: Science/Research
Classifier: Intended Audience :: Developers
Classifier: Topic :: Scientific/Engineering :: Mathematics
Classifier: Topic :: Software Development :: Libraries :: Python Modules
Classifier: License :: OSI Approved :: MIT License
Classifier: Programming Language :: Python :: 3
Classifier: Programming Language :: Python :: 3.8
Classifier: Programming Language :: Python :: 3.9
Classifier: Programming Language :: Python :: 3.10
Classifier: Programming Language :: Python :: 3.11
Requires-Python: >=3.8
License-File: LICENSE
Requires-Dist: numpy>=1.20.0
Requires-Dist: scipy>=1.7.0
Requires-Dist: pandas>=1.3.0
Requires-Dist: statsmodels>=0.13.0
Provides-Extra: dev
Requires-Dist: pytest>=7.0.0; extra == "dev"
Requires-Dist: pytest-cov>=3.0.0; extra == "dev"
Requires-Dist: black>=22.0.0; extra == "dev"
Requires-Dist: flake8>=4.0.0; extra == "dev"
Requires-Dist: mypy>=0.950; extra == "dev"
Provides-Extra: viz
Requires-Dist: matplotlib>=3.5.0; extra == "viz"
Dynamic: author
Dynamic: home-page
Dynamic: license-file
Dynamic: requires-python
